netpanda/__init__.py
netpanda/common.py
netpanda/netpanda.py
netpanda-0.0.6.dist-info/LICENSE
netpanda-0.0.6.dist-info/METADATA
netpanda-0.0.6.dist-info/WHEEL
netpanda-0.0.6.dist-info/entry_points.txt
netpanda-0.0.6.dist-info/top_level.txt
netpanda-0.0.6.dist-info/RECORD
