Metadata-Version: 2.1
Name: netpanda
Version: 0.0.6
Summary: A python package for geospatial analysis
Author-email: Shabiha Hossain <sabihahossain4105@gmail.com>
License: MIT License
Project-URL: Homepage, https://github.com/OmiimO05/netpanda
Keywords: netpanda
Classifier: Intended Audience :: Developers
Classifier: License :: OSI Approved :: MIT License
Classifier: Natural Language :: English
Classifier: Programming Language :: Python :: 3.8
Classifier: Programming Language :: Python :: 3.9
Classifier: Programming Language :: Python :: 3.10
Classifier: Programming Language :: Python :: 3.11
Classifier: Programming Language :: Python :: 3.12
Requires-Python: >=3.8
License-File: LICENSE
Requires-Dist: numpy
Requires-Dist: ipyleaflet
Requires-Dist: pandas
Requires-Dist: pyshp
Requires-Dist: geopandas
Provides-Extra: all
Requires-Dist: netpanda[extra] ; extra == 'all'
Provides-Extra: extra
Requires-Dist: pandas ; extra == 'extra'
